parsepro/__init__.py
parsepro/image_parser.py
parsepro/pdf_parser.py
parsepro-1.0.1.dist-info/METADATA
parsepro-1.0.1.dist-info/WHEEL
parsepro-1.0.1.dist-info/top_level.txt
parsepro-1.0.1.dist-info/RECORD
