Metadata-Version: 2.4
Name: parsepro
Version: 1.0.1
Summary: A library for parsing various file formats to  markdown format
Author-email: Jobanpreet Singh <singhjoban495@gmail.com>
License: MIT
Project-URL: Homepage, https://github.com/jobanpreet495/parsepro
Project-URL: Bug Tracker, https://github.com/jobanpreet495/parsepro/issues
Classifier: Programming Language :: Python :: 3
Classifier: License :: OSI Approved :: MIT License
Classifier: Operating System :: OS Independent
Requires-Python: >=3.10
Requires-Dist: together
Requires-Dist: pdf2image==1.17.0
Requires-Dist: PyPDF2==3.0.1
Requires-Dist: python-dotenv
